LICENSE
MANIFEST.in
README.md
pyproject.toml
setup.cfg
setup.py
import_export/__init__.py
import_export/apps.py
import_export/crypto.py
import_export/forms.py
import_export/funcs.py
import_export/models.py
import_export/multi_hooks.py
import_export/settings.py
import_export/tasks.py
import_export/util.py
import_export/wagtail_hooks.py
import_export/locale/nl/LC_MESSAGES/django.mo
import_export/locale/nl/LC_MESSAGES/django.po
import_export/migrations/0001_initial.py
import_export/migrations/0002_alter_databasedump_file.py
import_export/migrations/0003_alter_databasedump_file.py
import_export/migrations/__init__.py
import_export/migrations/__pycache__/0001_initial.cpython-311.pyc
import_export/migrations/__pycache__/0002_alter_databasedump_file.cpython-311.pyc
import_export/migrations/__pycache__/0003_alter_databasedump_file.cpython-311.pyc
import_export/migrations/__pycache__/__init__.cpython-311.pyc
import_export/static/import_export/confirm.js
import_export/static/import_export/export.js
import_export/static/import_export/import.js
import_export/static/import_export/import_export.css
import_export/templates/import_export/export.html
import_export/templates/import_export/import.html
import_export/templates/import_export/import_confirm.html
import_export/templates/import_export/task.html
import_export/tests/__init__.py
import_export/tests/test_crypto.py
import_export/tests/test_dump.py
sql_import_export.egg-info/PKG-INFO
sql_import_export.egg-info/SOURCES.txt
sql_import_export.egg-info/dependency_links.txt
sql_import_export.egg-info/requires.txt
sql_import_export.egg-info/top_level.txt