Metadata-Version: 2.1
Name: sql_import_export
Version: 1.0.2
Summary: An application to import or export your Wagtail site's database.
Home-page: https://github.com/Nigel2392/import_export
Author: Nigel
Author-email: nigel@goodadvice.it
License: GPL-3.0-only
Classifier: Environment :: Web Environment
Classifier: Framework :: Django
Classifier: Framework :: Django :: 4.2
Classifier: Framework :: Wagtail :: 5
Classifier: Framework :: Wagtail :: 6
Classifier: Intended Audience :: Developers
Classifier: License :: OSI Approved :: GNU General Public License v3 or later (GPLv3+)
Classifier: Operating System :: OS Independent
Classifier: Programming Language :: Python
Classifier: Programming Language :: Python :: 3
Classifier: Programming Language :: Python :: 3 :: Only
Classifier: Programming Language :: Python :: 3.8
Classifier: Programming Language :: Python :: 3.9
Classifier: Topic :: Internet :: WWW/HTTP
Classifier: Topic :: Internet :: WWW/HTTP :: Dynamic Content
Requires-Python: >=3.8
License-File: LICENSE
Requires-Dist: Django>=4.2
Requires-Dist: Wagtail>=5.0
Requires-Dist: celery>=5.3.1
Requires-Dist: django-celery-beat>=2.5.0
Requires-Dist: wagtail_panels>=1.0.0
Requires-Dist: wagtail-maintenance>=1.0.0
Requires-Dist: cryptography>=42.0.5
